MyLibrary111111/__init__.py
MyLibrary111111/my_functions.py
MyLibrary111111-1.2.dist-info/METADATA
MyLibrary111111-1.2.dist-info/WHEEL
MyLibrary111111-1.2.dist-info/top_level.txt
MyLibrary111111-1.2.dist-info/RECORD
