Metadata-Version: 2.1
Name: MyLibrary111111
Version: 1.2
Summary: Some words
Home-page: https://github.com/OFFdevil/PythonCourse2024/blob/HW1/hw_1/task1/nl.py
Author: ONdevil
Author-email: dplotnikovon@gmail.com
License: Plotnikov Licence
Platform: UNKNOWN
